badldap/__init__.py
badldap/__main__.py
badldap/_version.py
badldap/bloodhound.py
badldap/client.py
badldap/connection.py
badldap/commons/__init__.py
badldap/commons/adexplorer.py
badldap/commons/authbuilder.py
badldap/commons/common.py
badldap/commons/exceptions.py
badldap/commons/factory.py
badldap/commons/keycredential.py
badldap/commons/ldif.py
badldap/commons/plugin.py
badldap/commons/target.py
badldap/commons/utils.py
badldap/examples/__init__.py
badldap/examples/jsontest.py
badldap/examples/msldapbloodhound.py
badldap/examples/msldapclient.py
badldap/examples/msldapcompdnslist.py
badldap/examples/utils/__init__.py
badldap/examples/utils/completers.py
badldap/external/__init__.py
badldap/external/aiocmd/__init__.py
badldap/external/aiocmd/aiocmd/__init__.py
badldap/external/aiocmd/aiocmd/aiocmd.py
badldap/external/aiocmd/aiocmd/nested_completer.py
badldap/external/asciitree/__init__.py
badldap/external/asciitree/setup.py
badldap/external/asciitree/asciitree/__init__.py
badldap/external/asciitree/asciitree/drawing.py
badldap/external/asciitree/asciitree/traversal.py
badldap/external/asciitree/asciitree/util.py
badldap/external/bloodhoundpy/__init__.py
badldap/external/bloodhoundpy/acls.py
badldap/external/bloodhoundpy/resolver.py
badldap/external/bloodhoundpy/utils.py
badldap/external/bloodhoundpy/lib/__init__.py
badldap/external/bloodhoundpy/lib/cstruct.py
badldap/ldap_objects/__init__.py
badldap/ldap_objects/adca.py
badldap/ldap_objects/adcertificatetemplate.py
badldap/ldap_objects/adcomp.py
badldap/ldap_objects/adcontainer.py
badldap/ldap_objects/addmsa.py
badldap/ldap_objects/adenrollmentservice.py
badldap/ldap_objects/adgmsa.py
badldap/ldap_objects/adgpo.py
badldap/ldap_objects/adgroup.py
badldap/ldap_objects/adinfo.py
badldap/ldap_objects/adou.py
badldap/ldap_objects/adschemaentry.py
badldap/ldap_objects/adsec.py
badldap/ldap_objects/adtrust.py
badldap/ldap_objects/aduser.py
badldap/ldap_objects/common.py
badldap/network/__init__.py
badldap-0.7.4.dist-info/licenses/LICENSE
badldap-0.7.4.dist-info/METADATA
badldap-0.7.4.dist-info/WHEEL
badldap-0.7.4.dist-info/entry_points.txt
badldap-0.7.4.dist-info/top_level.txt
badldap-0.7.4.dist-info/RECORD
